CHANGELOG.txt
LICENSE.txt
MANIFEST.in
README.rst
buildout.cfg
setup.py
versions.cfg
django_tagging_plateiq.egg-info/PKG-INFO
django_tagging_plateiq.egg-info/SOURCES.txt
django_tagging_plateiq.egg-info/dependency_links.txt
django_tagging_plateiq.egg-info/not-zip-safe
django_tagging_plateiq.egg-info/top_level.txt
docs/Makefile
docs/conf.py
docs/index.rst
tagging/__init__.py
tagging/admin.py
tagging/apps.py
tagging/fields.py
tagging/forms.py
tagging/generic.py
tagging/managers.py
tagging/models.py
tagging/registry.py
tagging/settings.py
tagging/utils.py
tagging/views.py
tagging/migrations/0001_initial.py
tagging/migrations/0002_on_delete.py
tagging/migrations/0003_auto_20170423_1143.py
tagging/migrations/0004_auto_20170802_1747.py
tagging/migrations/0005_adapt_max_tag_length.py
tagging/migrations/__init__.py
tagging/templatetags/__init__.py
tagging/templatetags/tagging_tags.py
tagging/tests/__init__.py
tagging/tests/models.py
tagging/tests/settings.py
tagging/tests/tags.txt
tagging/tests/tests.py
tagging/tests/urls.py
tagging/tests/utils.py