Metadata-Version: 1.2
Name: django-tagging-plateiq
Version: 0.6.0
Summary: Generic tagging application for Django with support for CharText IDs
Home-page: https://github.com/inzunzo/django-tagging-qubiqle
Author: Jonathan Buchanan
Author-email: jonathan.buchanan@gmail.com
Maintainer: Arturo Inzunza
Maintainer-email: arturo@plateiq.com
License: BSD License
Keywords: django,tag,tagging
Platform: UNKNOWN
Classifier: Framework :: Django
Classifier: Environment :: Web Environment
Classifier: Operating System :: OS Independent
Classifier: Development Status :: 5 - Production/Stable
Classifier: Intended Audience :: Developers
Classifier: License :: OSI Approved :: BSD License
Classifier: Programming Language :: Python
Classifier: Programming Language :: Python :: 3
Classifier: Topic :: Utilities
Classifier: Topic :: Software Development :: Libraries :: Python Modules
